defendatron/__init__.py
defendatron/nullscream_tracker.py
defendatron-0.1.11.dist-info/licenses/LICENSE
defendatron-0.1.11.dist-info/METADATA
defendatron-0.1.11.dist-info/WHEEL
defendatron-0.1.11.dist-info/top_level.txt
defendatron-0.1.11.dist-info/RECORD
