Metadata-Version: 2.4
Name: defendatron
Version: 0.1.11
Home-page: https://github.com/Capsize-Games/defendatron
Author: Capsize LLC
Author-email: contact@capsizegames.com
License: GPL-3.0
Requires-Python: >=3.10.0
License-File: LICENSE
Requires-Dist: nullscream==0.1.5
Requires-Dist: darklock==0.1.6
Requires-Dist: shadowlogger==0.1.1
Dynamic: author
Dynamic: author-email
Dynamic: description
Dynamic: description-content-type
Dynamic: home-page
Dynamic: keywords
Dynamic: license
Dynamic: license-file
Dynamic: requires-dist
Dynamic: requires-python
